flask_sri.py
setup.py
Flask_SRI.egg-info/PKG-INFO
Flask_SRI.egg-info/SOURCES.txt
Flask_SRI.egg-info/dependency_links.txt
Flask_SRI.egg-info/top_level.txt