Metadata-Version: 1.0
Name: Flask-SRI
Version: 0.1.0
Summary: Flask-SRI
Home-page: https://github.com/raicheff/flask-sri
Author: Boris Raicheff
Author-email: b@raicheff.com
License: UNKNOWN
Platform: UNKNOWN
